patchlab/__init__.py
patchlab/admin.py
patchlab/apps.py
patchlab/bridge.py
patchlab/celery.py
patchlab/events.py
patchlab/gitlab2email.py
patchlab/models.py
patchlab/tasks.py
patchlab/urls.py
patchlab/management/__init__.py
patchlab/management/commands/__init__.py
patchlab/management/commands/clone.py
patchlab/management/commands/series2gitlab.py
patchlab/migrations/0001_initial.py
patchlab/migrations/0002_drop_unique_commit.py
patchlab/migrations/0003_add_submission_version.py
patchlab/migrations/0004_auto_20200428_0559.py
patchlab/migrations/__init__.py
patchlab/settings/__init__.py
patchlab/settings/base.py
patchlab/settings/ci.py
patchlab/tests/__init__.py
patchlab/tests/test_bridge.py
patchlab/tests/test_events.py
patchlab/tests/test_gitlab2email.py
patchlab/tests/test_models.py
patchlab/tests/test_tasks.py
patchlab/views/__init__.py
patchlab/views/gitlab.py
patchlab-0.6.2.dist-info/LICENSE
patchlab-0.6.2.dist-info/METADATA
patchlab-0.6.2.dist-info/WHEEL
patchlab-0.6.2.dist-info/top_level.txt
patchlab-0.6.2.dist-info/RECORD
