Metadata-Version: 2.1
Name: patchlab
Version: 0.6.2
Summary: A Django application designed to bridge Patchwork to GitLab
Home-page: https://github.com/jeremycline/patchlab
Maintainer: Jeremy Cline
Maintainer-email: jcline@fedoraproject.org
License: GPLv2+
Keywords: patchwork,gitlab,django
Platform: GNU/Linux
Classifier: Development Status :: 5 - Production/Stable
Classifier: License :: OSI Approved :: GNU General Public License v2 or later (GPLv2+)
Classifier: Operating System :: POSIX :: Linux
Classifier: Programming Language :: Python :: 3
Classifier: Programming Language :: Python :: 3.6
Classifier: Programming Language :: Python :: 3.7
Requires-Dist: backoff
Requires-Dist: celery
Requires-Dist: django
Requires-Dist: requests
Requires-Dist: python-gitlab
